mkdocs_nodegraph/__init__.py
mkdocs_nodegraph/plugin.py
mkdocs_nodegraph/nodegraph/__init__.py
mkdocs_nodegraph/nodegraph/generate_graph.py
mkdocs_nodegraph/nodegraph/graph_opts.json
mkdocs_nodegraph/nodegraph/mdfile.py
mkdocs_nodegraph/nodegraph/mdparser.py
mkdocs_nodegraph/nodegraph/pyvis_opts.js
mkdocs_nodegraph/nodegraph/templates/__init__.py
mkdocs_nodegraph/nodegraph/templates/template.html
mkdocs_nodegraph-0.4.1.dist-info/METADATA
mkdocs_nodegraph-0.4.1.dist-info/WHEEL
mkdocs_nodegraph-0.4.1.dist-info/entry_points.txt
mkdocs_nodegraph-0.4.1.dist-info/top_level.txt
mkdocs_nodegraph-0.4.1.dist-info/RECORD
