Metadata-Version: 2.1
Name: mkdocs-nodegraph
Version: 0.4.1
Summary: Node Graph plugin for Mkdocs Material
Home-page: https://yonge123.github.io/mkdocs-nodegraph/nodegraph.html
Author: JeongYong Hwang
Author-email: yonge123@gmail.com
License: MIT
Project-URL: Source, https://github.com/yonge123/mkdocs-nodegraph/tree/master
Project-URL: Bug Tracker, https://github.com/yonge123/mkdocs-nodegraph/issues
Project-URL: Documentation, https://github.com/yonge123/mkdocs-nodegraph/tree/master
Keywords: mkdocs-nodegraph,mkdocs,mkdocs-material,markdown node,graph,nodenetwork,nodeview,graphview,networkgraph,plugin,nodegraph,markdown
Requires-Python: >=3.9
Requires-Dist: mkdocs >=1.4.0
Requires-Dist: mkdocs-material >=9.5.31
Requires-Dist: pyembed-markdown >=1.1.0
Requires-Dist: mkdocs-glightbox >=0.4.0
Requires-Dist: pyvis >=0.3.0
Requires-Dist: PyYAML >=6.0.2
